{
	"__header__": {
		"fileType": "LEd Project JSON",
		"app": "LEd",
		"appAuthor": "Sebastien Benard",
		"appVersion": "0.5.0-beta-debug",
		"url": "https://deepnight.net/tools/led-2d-level-editor/"
	},
	"jsonVersion": "0.5.0",
	"defaultPivotX": 0,
	"defaultPivotY": 0,
	"defaultGridSize": 16,
	"bgColor": "#222225",
	"nextUid": 37,
	"minifyJson": false,
	"exportTiled": false,
	"defs": {
		"layers": [
			{
				"__type": "IntGrid",
				"identifier": "IntGrid",
				"type": "IntGrid",
				"uid": 2,
				"gridSize": 16,
				"displayOpacity": 1,
				"pxOffsetX": 0,
				"pxOffsetY": 0,
				"intGridValues": [{ "identifier": "walls", "color": "#FFFFFF" }],
				"autoTilesetDefUid": 1,
				"autoRuleGroups": [
					{
						"uid": 12,
						"name": "Stamp",
						"active": true,
						"collapsed": false,
						"rules": [
							{
								"uid": 13,
								"active": true,
								"size": 3,
								"tileIds": [22,32,23,33],
								"chance": 1,
								"breakOnMatch": true,
								"pattern": [0,0,0,0,1,1,0,1,1],
								"flipX": false,
								"flipY": false,
								"xModulo": 2,
								"yModulo": 2,
								"checker": "None",
								"tileMode": "Stamp",
								"pivotX": 0,
								"pivotY": 0,
								"perlinActive": false,
								"perlinSeed": 3897482,
								"perlinScale": 0.2,
								"perlinOctaves": 2
							}
						]
					},
					{
						"uid": 10,
						"name": "Wall base",
						"active": true,
						"collapsed": false,
						"rules": [
							{
								"uid": 11,
								"active": true,
								"size": 1,
								"tileIds": [72],
								"chance": 1,
								"breakOnMatch": true,
								"pattern": [1],
								"flipX": false,
								"flipY": false,
								"xModulo": 1,
								"yModulo": 1,
								"checker": "None",
								"tileMode": "Single",
								"pivotX": 0,
								"pivotY": 0,
								"perlinActive": false,
								"perlinSeed": 7959157,
								"perlinScale": 0.2,
								"perlinOctaves": 2
							}
						]
					}
				],
				"autoSourceLayerDefUid": null,
				"tilesetDefUid": null,
				"tilePivotX": 0,
				"tilePivotY": 0
			},
			{
				"__type": "Entities",
				"identifier": "Entities",
				"type": "Entities",
				"uid": 35,
				"gridSize": 16,
				"displayOpacity": 1,
				"pxOffsetX": 0,
				"pxOffsetY": 0,
				"intGridValues": [{ "identifier": null, "color": "#000000" }],
				"autoTilesetDefUid": null,
				"autoRuleGroups": [],
				"autoSourceLayerDefUid": null,
				"tilesetDefUid": null,
				"tilePivotX": 0,
				"tilePivotY": 0
			}
		],
		"entities": [
			{
				"identifier": "Label",
				"uid": 33,
				"width": 16,
				"height": 16,
				"color": "#000000",
				"renderMode": "Rectangle",
				"showName": false,
				"tilesetId": null,
				"tileId": null,
				"tileRenderMode": "Stretch",
				"maxPerLevel": 0,
				"limitBehavior": "DiscardOldOnes",
				"pivotX": 0.5,
				"pivotY": 0.5,
				"fieldDefs": [
					{
						"identifier": "Text",
						"__type": "String",
						"uid": 34,
						"type": "F_Text",
						"isArray": false,
						"canBeNull": false,
						"arrayMinLength": null,
						"arrayMaxLength": null,
						"editorDisplayMode": "ValueOnly",
						"editorDisplayPos": "Center",
						"editorAlwaysShow": false,
						"min": null,
						"max": null,
						"defaultOverride": null
					},
					{
						"identifier": "Color",
						"__type": "Color",
						"uid": 36,
						"type": "F_Color",
						"isArray": false,
						"canBeNull": false,
						"arrayMinLength": null,
						"arrayMaxLength": null,
						"editorDisplayMode": "Hidden",
						"editorDisplayPos": "Above",
						"editorAlwaysShow": false,
						"min": null,
						"max": null,
						"defaultOverride": { "id": "V_Int", "params": [16777215] }
					}
				]
			}
		],
		"tilesets": [
			{
				"identifier": "Inca_front_by_Kronbits",
				"uid": 1,
				"relPath": "Inca_front_by_Kronbits.png",
				"pxWid": 160,
				"pxHei": 224,
				"tileGridSize": 16,
				"spacing": 0,
				"padding": 0,
				"opaqueTiles": [
					0,
					1,
					2,
					3,
					4,
					5,
					6,
					7,
					8,
					9,
					10,
					11,
					12,
					13,
					14,
					15,
					16,
					17,
					18,
					19,
					20,
					21,
					22,
					23,
					24,
					25,
					26,
					27,
					28,
					29,
					30,
					31,
					32,
					33,
					34,
					35,
					36,
					37,
					38,
					39,
					40,
					41,
					42,
					43,
					44,
					45,
					46,
					47,
					48,
					49,
					50,
					51,
					52,
					53,
					54,
					55,
					56,
					57,
					58,
					59,
					60,
					61,
					62,
					63,
					64,
					65,
					66,
					67,
					68,
					69,
					70,
					71,
					72,
					73,
					74,
					75,
					76,
					77,
					78,
					79,
					80,
					81,
					82,
					83,
					84,
					85,
					86,
					87,
					88,
					89,
					90,
					91,
					92,
					93,
					94,
					95,
					96,
					97,
					98,
					99
				],
				"savedSelections": []
			}
		],
		"enums": [],
		"externalEnums": []
	},
	"levels": [{
		"identifier": "Stamps",
		"uid": 0,
		"pxWid": 272,
		"pxHei": 288,
		"layerInstances": [
			{
				"__identifier": "IntGrid",
				"__type": "IntGrid",
				"__cWid": 17,
				"__cHei": 18,
				"__gridSize": 16,
				"__opacity": 1,
				"__pxTotalOffsetX": 0,
				"__pxTotalOffsetY": 0,
				"levelId": 0,
				"layerDefUid": 2,
				"pxOffsetX": 0,
				"pxOffsetY": 0,
				"intGrid": [
					{ "coordId": 76, "v": 0 },
					{ "coordId": 77, "v": 0 },
					{ "coordId": 78, "v": 0 },
					{ "coordId": 79, "v": 0 },
					{ "coordId": 80, "v": 0 },
					{ "coordId": 81, "v": 0 },
					{ "coordId": 93, "v": 0 },
					{ "coordId": 94, "v": 0 },
					{ "coordId": 95, "v": 0 },
					{ "coordId": 96, "v": 0 },
					{ "coordId": 97, "v": 0 },
					{ "coordId": 98, "v": 0 },
					{ "coordId": 142, "v": 0 },
					{ "coordId": 143, "v": 0 },
					{ "coordId": 145, "v": 0 },
					{ "coordId": 146, "v": 0 },
					{ "coordId": 147, "v": 0 },
					{ "coordId": 148, "v": 0 },
					{ "coordId": 157, "v": 0 },
					{ "coordId": 158, "v": 0 },
					{ "coordId": 159, "v": 0 },
					{ "coordId": 160, "v": 0 },
					{ "coordId": 162, "v": 0 },
					{ "coordId": 163, "v": 0 },
					{ "coordId": 164, "v": 0 },
					{ "coordId": 165, "v": 0 },
					{ "coordId": 172, "v": 0 },
					{ "coordId": 173, "v": 0 },
					{ "coordId": 174, "v": 0 },
					{ "coordId": 175, "v": 0 },
					{ "coordId": 176, "v": 0 },
					{ "coordId": 177, "v": 0 },
					{ "coordId": 179, "v": 0 },
					{ "coordId": 180, "v": 0 },
					{ "coordId": 181, "v": 0 },
					{ "coordId": 182, "v": 0 },
					{ "coordId": 189, "v": 0 },
					{ "coordId": 190, "v": 0 },
					{ "coordId": 191, "v": 0 },
					{ "coordId": 192, "v": 0 },
					{ "coordId": 193, "v": 0 },
					{ "coordId": 194, "v": 0 },
					{ "coordId": 196, "v": 0 },
					{ "coordId": 197, "v": 0 },
					{ "coordId": 198, "v": 0 },
					{ "coordId": 199, "v": 0 },
					{ "coordId": 206, "v": 0 },
					{ "coordId": 207, "v": 0 },
					{ "coordId": 208, "v": 0 },
					{ "coordId": 209, "v": 0 },
					{ "coordId": 210, "v": 0 },
					{ "coordId": 211, "v": 0 },
					{ "coordId": 225, "v": 0 },
					{ "coordId": 226, "v": 0 },
					{ "coordId": 227, "v": 0 },
					{ "coordId": 228, "v": 0 },
					{ "coordId": 231, "v": 0 },
					{ "coordId": 232, "v": 0 },
					{ "coordId": 233, "v": 0 },
					{ "coordId": 234, "v": 0 },
					{ "coordId": 235, "v": 0 },
					{ "coordId": 242, "v": 0 },
					{ "coordId": 243, "v": 0 },
					{ "coordId": 244, "v": 0 },
					{ "coordId": 245, "v": 0 },
					{ "coordId": 249, "v": 0 },
					{ "coordId": 250, "v": 0 },
					{ "coordId": 251, "v": 0 },
					{ "coordId": 252, "v": 0 },
					{ "coordId": 266, "v": 0 },
					{ "coordId": 267, "v": 0 },
					{ "coordId": 268, "v": 0 },
					{ "coordId": 269, "v": 0 },
					{ "coordId": 283, "v": 0 },
					{ "coordId": 284, "v": 0 },
					{ "coordId": 285, "v": 0 },
					{ "coordId": 286, "v": 0 }
				],
				"autoLayerTiles": [
					{ "px": [144,64], "src": [32,112], "f": 0, "d": [11,77,72] },
					{ "px": [176,64], "src": [32,112], "f": 0, "d": [11,79,72] },
					{ "px": [208,64], "src": [32,112], "f": 0, "d": [11,81,72] },
					{ "px": [128,80], "src": [32,112], "f": 0, "d": [11,93,72] },
					{ "px": [144,80], "src": [32,112], "f": 0, "d": [11,94,72] },
					{ "px": [160,80], "src": [32,112], "f": 0, "d": [11,95,72] },
					{ "px": [176,80], "src": [32,112], "f": 0, "d": [11,96,72] },
					{ "px": [192,80], "src": [32,112], "f": 0, "d": [11,97,72] },
					{ "px": [208,80], "src": [32,112], "f": 0, "d": [11,98,72] },
					{ "px": [112,128], "src": [32,112], "f": 0, "d": [11,143,72] },
					{ "px": [144,128], "src": [32,112], "f": 0, "d": [11,145,72] },
					{ "px": [176,128], "src": [32,112], "f": 0, "d": [11,147,72] },
					{ "px": [192,128], "src": [32,112], "f": 0, "d": [11,148,72] },
					{ "px": [64,144], "src": [32,112], "f": 0, "d": [11,157,72] },
					{ "px": [80,144], "src": [32,112], "f": 0, "d": [11,158,72] },
					{ "px": [96,144], "src": [32,112], "f": 0, "d": [11,159,72] },
					{ "px": [112,144], "src": [32,112], "f": 0, "d": [11,160,72] },
					{ "px": [144,144], "src": [32,112], "f": 0, "d": [11,162,72] },
					{ "px": [160,144], "src": [32,112], "f": 0, "d": [11,163,72] },
					{ "px": [176,144], "src": [32,112], "f": 0, "d": [11,164,72] },
					{ "px": [192,144], "src": [32,112], "f": 0, "d": [11,165,72] },
					{ "px": [48,160], "src": [32,112], "f": 0, "d": [11,173,72] },
					{ "px": [80,160], "src": [32,112], "f": 0, "d": [11,175,72] },
					{ "px": [112,160], "src": [32,112], "f": 0, "d": [11,177,72] },
					{ "px": [144,160], "src": [32,112], "f": 0, "d": [11,179,72] },
					{ "px": [176,160], "src": [32,112], "f": 0, "d": [11,181,72] },
					{ "px": [192,160], "src": [32,112], "f": 0, "d": [11,182,72] },
					{ "px": [32,176], "src": [32,112], "f": 0, "d": [11,189,72] },
					{ "px": [48,176], "src": [32,112], "f": 0, "d": [11,190,72] },
					{ "px": [64,176], "src": [32,112], "f": 0, "d": [11,191,72] },
					{ "px": [80,176], "src": [32,112], "f": 0, "d": [11,192,72] },
					{ "px": [96,176], "src": [32,112], "f": 0, "d": [11,193,72] },
					{ "px": [112,176], "src": [32,112], "f": 0, "d": [11,194,72] },
					{ "px": [144,176], "src": [32,112], "f": 0, "d": [11,196,72] },
					{ "px": [160,176], "src": [32,112], "f": 0, "d": [11,197,72] },
					{ "px": [176,176], "src": [32,112], "f": 0, "d": [11,198,72] },
					{ "px": [192,176], "src": [32,112], "f": 0, "d": [11,199,72] },
					{ "px": [32,192], "src": [32,112], "f": 0, "d": [11,206,72] },
					{ "px": [48,192], "src": [32,112], "f": 0, "d": [11,207,72] },
					{ "px": [80,192], "src": [32,112], "f": 0, "d": [11,209,72] },
					{ "px": [112,192], "src": [32,112], "f": 0, "d": [11,211,72] },
					{ "px": [64,208], "src": [32,112], "f": 0, "d": [11,225,72] },
					{ "px": [80,208], "src": [32,112], "f": 0, "d": [11,226,72] },
					{ "px": [96,208], "src": [32,112], "f": 0, "d": [11,227,72] },
					{ "px": [112,208], "src": [32,112], "f": 0, "d": [11,228,72] },
					{ "px": [160,208], "src": [32,112], "f": 0, "d": [11,231,72] },
					{ "px": [176,208], "src": [32,112], "f": 0, "d": [11,232,72] },
					{ "px": [192,208], "src": [32,112], "f": 0, "d": [11,233,72] },
					{ "px": [208,208], "src": [32,112], "f": 0, "d": [11,234,72] },
					{ "px": [224,208], "src": [32,112], "f": 0, "d": [11,235,72] },
					{ "px": [64,224], "src": [32,112], "f": 0, "d": [11,242,72] },
					{ "px": [80,224], "src": [32,112], "f": 0, "d": [11,243,72] },
					{ "px": [96,224], "src": [32,112], "f": 0, "d": [11,244,72] },
					{ "px": [112,224], "src": [32,112], "f": 0, "d": [11,245,72] },
					{ "px": [176,224], "src": [32,112], "f": 0, "d": [11,249,72] },
					{ "px": [208,224], "src": [32,112], "f": 0, "d": [11,251,72] },
					{ "px": [224,224], "src": [32,112], "f": 0, "d": [11,252,72] },
					{ "px": [176,240], "src": [32,112], "f": 0, "d": [11,266,72] },
					{ "px": [192,240], "src": [32,112], "f": 0, "d": [11,267,72] },
					{ "px": [208,240], "src": [32,112], "f": 0, "d": [11,268,72] },
					{ "px": [224,240], "src": [32,112], "f": 0, "d": [11,269,72] },
					{ "px": [176,256], "src": [32,112], "f": 0, "d": [11,283,72] },
					{ "px": [192,256], "src": [32,112], "f": 0, "d": [11,284,72] },
					{ "px": [208,256], "src": [32,112], "f": 0, "d": [11,285,72] },
					{ "px": [224,256], "src": [32,112], "f": 0, "d": [11,286,72] },
					{ "px": [128,64], "src": [32,32], "f": 0, "d": [13,76,22] },
					{ "px": [128,80], "src": [32,48], "f": 0, "d": [13,76,32] },
					{ "px": [144,64], "src": [48,32], "f": 0, "d": [13,76,23] },
					{ "px": [144,80], "src": [48,48], "f": 0, "d": [13,76,33] },
					{ "px": [160,64], "src": [32,32], "f": 0, "d": [13,78,22] },
					{ "px": [160,80], "src": [32,48], "f": 0, "d": [13,78,32] },
					{ "px": [176,64], "src": [48,32], "f": 0, "d": [13,78,23] },
					{ "px": [176,80], "src": [48,48], "f": 0, "d": [13,78,33] },
					{ "px": [192,64], "src": [32,32], "f": 0, "d": [13,80,22] },
					{ "px": [192,80], "src": [32,48], "f": 0, "d": [13,80,32] },
					{ "px": [208,64], "src": [48,32], "f": 0, "d": [13,80,23] },
					{ "px": [208,80], "src": [48,48], "f": 0, "d": [13,80,33] },
					{ "px": [96,128], "src": [32,32], "f": 0, "d": [13,142,22] },
					{ "px": [96,144], "src": [32,48], "f": 0, "d": [13,142,32] },
					{ "px": [112,128], "src": [48,32], "f": 0, "d": [13,142,23] },
					{ "px": [112,144], "src": [48,48], "f": 0, "d": [13,142,33] },
					{ "px": [160,128], "src": [32,32], "f": 0, "d": [13,146,22] },
					{ "px": [160,144], "src": [32,48], "f": 0, "d": [13,146,32] },
					{ "px": [176,128], "src": [48,32], "f": 0, "d": [13,146,23] },
					{ "px": [176,144], "src": [48,48], "f": 0, "d": [13,146,33] },
					{ "px": [32,160], "src": [32,32], "f": 0, "d": [13,172,22] },
					{ "px": [32,176], "src": [32,48], "f": 0, "d": [13,172,32] },
					{ "px": [48,160], "src": [48,32], "f": 0, "d": [13,172,23] },
					{ "px": [48,176], "src": [48,48], "f": 0, "d": [13,172,33] },
					{ "px": [64,160], "src": [32,32], "f": 0, "d": [13,174,22] },
					{ "px": [64,176], "src": [32,48], "f": 0, "d": [13,174,32] },
					{ "px": [80,160], "src": [48,32], "f": 0, "d": [13,174,23] },
					{ "px": [80,176], "src": [48,48], "f": 0, "d": [13,174,33] },
					{ "px": [96,160], "src": [32,32], "f": 0, "d": [13,176,22] },
					{ "px": [96,176], "src": [32,48], "f": 0, "d": [13,176,32] },
					{ "px": [112,160], "src": [48,32], "f": 0, "d": [13,176,23] },
					{ "px": [112,176], "src": [48,48], "f": 0, "d": [13,176,33] },
					{ "px": [160,160], "src": [32,32], "f": 0, "d": [13,180,22] },
					{ "px": [160,176], "src": [32,48], "f": 0, "d": [13,180,32] },
					{ "px": [176,160], "src": [48,32], "f": 0, "d": [13,180,23] },
					{ "px": [176,176], "src": [48,48], "f": 0, "d": [13,180,33] },
					{ "px": [64,192], "src": [32,32], "f": 0, "d": [13,208,22] },
					{ "px": [64,208], "src": [32,48], "f": 0, "d": [13,208,32] },
					{ "px": [80,192], "src": [48,32], "f": 0, "d": [13,208,23] },
					{ "px": [80,208], "src": [48,48], "f": 0, "d": [13,208,33] },
					{ "px": [96,192], "src": [32,32], "f": 0, "d": [13,210,22] },
					{ "px": [96,208], "src": [32,48], "f": 0, "d": [13,210,32] },
					{ "px": [112,192], "src": [48,32], "f": 0, "d": [13,210,23] },
					{ "px": [112,208], "src": [48,48], "f": 0, "d": [13,210,33] },
					{ "px": [192,224], "src": [32,32], "f": 0, "d": [13,250,22] },
					{ "px": [192,240], "src": [32,48], "f": 0, "d": [13,250,32] },
					{ "px": [208,224], "src": [48,32], "f": 0, "d": [13,250,23] },
					{ "px": [208,240], "src": [48,48], "f": 0, "d": [13,250,33] }
				],
				"seed": 256018,
				"gridTiles": [],
				"entityInstances": []
			},
			{
				"__identifier": "Entities",
				"__type": "Entities",
				"__cWid": 17,
				"__cHei": 18,
				"__gridSize": 16,
				"__opacity": 1,
				"__pxTotalOffsetX": 0,
				"__pxTotalOffsetY": 0,
				"levelId": 0,
				"layerDefUid": 35,
				"pxOffsetX": 0,
				"pxOffsetY": 0,
				"intGrid": [],
				"autoLayerTiles": [],
				"seed": 4238306,
				"gridTiles": [],
				"entityInstances": [{ "__identifier": "Label", "__grid": [8,1], "__tile": null, "defUid": 33, "px": [136,24], "fieldInstances": [
					{
						"__identifier": "Text",
						"__value": "\"STAMPS\" are groups of multiple tiles that are generated by RULES.\\n\\nClick on the RULES button on the left to see them.",
						"__type": "String",
						"defUid": 34,
						"realEditorValues": [{
							"id": "V_String",
							"params": [
								"\"STAMPS\" are groups of multiple tiles that are generated by RULES.\\n\\nClick on the RULES button on the left to see them."
							]
						}]
					},
					{
						"__identifier": "Color",
						"__value": "#FFD500",
						"__type": "Color",
						"defUid": 36,
						"realEditorValues": [{ "id": "V_Int", "params": [16766208] }]
					}
				] }]
			}
		]
	}]
}